CHANGES.rst
LICENSE
MANIFEST.in
NOTICE
README.rst
setup.py
src/ralph_pricing/__init__.py
src/ralph_pricing/admin.py
src/ralph_pricing/forms.py
src/ralph_pricing/menus.py
src/ralph_pricing/models.py
src/ralph_pricing/openstack.py
src/ralph_pricing/splunk.py
src/ralph_pricing/urls.py
src/ralph_pricing.egg-info/PKG-INFO
src/ralph_pricing.egg-info/SOURCES.txt
src/ralph_pricing.egg-info/dependency_links.txt
src/ralph_pricing.egg-info/entry_points.txt
src/ralph_pricing.egg-info/not-zip-safe
src/ralph_pricing.egg-info/requires.txt
src/ralph_pricing.egg-info/top_level.txt
src/ralph_pricing/management/__init__.py
src/ralph_pricing/management/commands/__init__.py
src/ralph_pricing/management/commands/pricing_fix_blades.py
src/ralph_pricing/management/commands/pricing_sync.py
src/ralph_pricing/migrations/0001_initial.py
src/ralph_pricing/migrations/0002_auto__add_field_venture_symbol.py
src/ralph_pricing/migrations/0003_auto__add_field_usagetype_average__add_field_usagetype_show_value_perc.py
src/ralph_pricing/migrations/0004_auto__add_field_dailydevice_deprecation_rate__add_field_dailypart_depr.py
src/ralph_pricing/migrations/0005_auto__add_splunkname__add_unique_splunkname_splunk_name_pricing_device.py
src/ralph_pricing/migrations/0006_auto__add_field_venture_business_segment__add_field_venture_pricing_ce.py
src/ralph_pricing/migrations/0007_auto__del_field_venture_pricing_center__add_field_venture_profit_cente.py
src/ralph_pricing/migrations/0008_auto__del_unique_device_barcode__del_unique_device_sn.py
src/ralph_pricing/migrations/0009_auto__add_field_usagetype_symbol.py
src/ralph_pricing/migrations/0010_auto__add_field_dailyusage_total.py
src/ralph_pricing/migrations/0011_auto__chg_field_dailyusage_date.py
src/ralph_pricing/migrations/0012_auto__del_unique_dailyusage_date_type_pricing_device__add_unique_daily.py
src/ralph_pricing/migrations/__init__.py
src/ralph_pricing/plugins/__init__.py
src/ralph_pricing/plugins/assets.py
src/ralph_pricing/plugins/assets_part.py
src/ralph_pricing/plugins/cores.py
src/ralph_pricing/plugins/devices.py
src/ralph_pricing/plugins/extra_cost.py
src/ralph_pricing/plugins/hamster.py
src/ralph_pricing/plugins/import_devices.py
src/ralph_pricing/plugins/openstack.py
src/ralph_pricing/plugins/scaleme.py
